mu_alpha_zero/__init__.py
mu_alpha_zero/config.py
mu_alpha_zero/mem_buffer.py
mu_alpha_zero/prepare_for_upload.py
mu_alpha_zero/root.root
mu_alpha_zero/save_best_params.py
mu_alpha_zero/shared_storage_manager.py
mu_alpha_zero/start_jobs.py
mu_alpha_zero/trainer.py
mu_alpha_zero/AlphaZero/__init__.py
mu_alpha_zero/AlphaZero/alpha_zero.py
mu_alpha_zero/AlphaZero/checkpointer.py
mu_alpha_zero/AlphaZero/constants.py
mu_alpha_zero/AlphaZero/logger.py
mu_alpha_zero/AlphaZero/utils.py
mu_alpha_zero/AlphaZero/Arena/__init__.py
mu_alpha_zero/AlphaZero/Arena/arena.py
mu_alpha_zero/AlphaZero/Arena/players.py
mu_alpha_zero/AlphaZero/MCTS/__init__.py
mu_alpha_zero/AlphaZero/MCTS/az_node.py
mu_alpha_zero/AlphaZero/MCTS/az_search_tree.py
mu_alpha_zero/AlphaZero/Network/__init__.py
mu_alpha_zero/AlphaZero/Network/nnet.py
mu_alpha_zero/Game/__init__.py
mu_alpha_zero/Game/asteroids.py
mu_alpha_zero/Game/tictactoe_game.py
mu_alpha_zero/General/__init__.py
mu_alpha_zero/General/arena.py
mu_alpha_zero/General/az_game.py
mu_alpha_zero/General/memory.py
mu_alpha_zero/General/mz_game.py
mu_alpha_zero/General/network.py
mu_alpha_zero/General/search_tree.py
mu_alpha_zero/General/utils.py
mu_alpha_zero/Hooks/__init__.py
mu_alpha_zero/Hooks/hook_callables.py
mu_alpha_zero/Hooks/hook_manager.py
mu_alpha_zero/Hooks/hook_point.py
mu_alpha_zero/MuZero/__init__.py
mu_alpha_zero/MuZero/lazy_arrays.py
mu_alpha_zero/MuZero/muzero.py
mu_alpha_zero/MuZero/utils.py
mu_alpha_zero/MuZero/MZ_Arena/__init__.py
mu_alpha_zero/MuZero/MZ_Arena/arena.py
mu_alpha_zero/MuZero/MZ_MCTS/__init__.py
mu_alpha_zero/MuZero/MZ_MCTS/mz_node.py
mu_alpha_zero/MuZero/MZ_MCTS/mz_search_tree.py
mu_alpha_zero/MuZero/MinimaxOpponent/__init__.py
mu_alpha_zero/MuZero/MinimaxOpponent/board.py
mu_alpha_zero/MuZero/MinimaxOpponent/player.py
mu_alpha_zero/MuZero/Network/__init__.py
mu_alpha_zero/MuZero/Network/networks.py
mu_alpha_zero/PerfectConnect4Negamax/__init__.py
mu_alpha_zero/PerfectConnect4Negamax/board.py
mu_alpha_zero_library-1.0.9.6.dist-info/LICENSE
mu_alpha_zero_library-1.0.9.6.dist-info/METADATA
mu_alpha_zero_library-1.0.9.6.dist-info/WHEEL
mu_alpha_zero_library-1.0.9.6.dist-info/top_level.txt
mu_alpha_zero_library-1.0.9.6.dist-info/RECORD
