Metadata-Version: 2.1
Name: mu-alpha-zero-library
Version: 1.0.9.6
Summary: Library for running and training MuZero and AlphaZero models.
Home-page: https://github.com/Skirlax/MuAlphaZeroLibrary
Author: Skyr
License-File: LICENSE
Requires-Dist: numpy
Requires-Dist: pygame~=2.1.3
Requires-Dist: optuna~=3.2.0
Requires-Dist: gym[accept-rom-license,atari]
Requires-Dist: dill
Requires-Dist: gymnasium[atari]
Requires-Dist: diskcache
Requires-Dist: pushbullet-python
Requires-Dist: torchvision
Requires-Dist: torchaudio
Requires-Dist: torch
Requires-Dist: wandb
Requires-Dist: multiprocess
